{
    "Adamson": "90000",
    "Angeles University": "74500",
    "APC": "142500",
    "Assumption": "145000",
    "Ateneo de Davao": "92000",
    "Ateneo de Manila": "170000",
    "Ateneo de Naga": "60000",
    "Cebu Doctors": "83000",
    "CSB": "195000",
    "DLSU Lipa": "105000",
    "DLSU Manila": "217500",
    "Don Bosco": "98000",
    "FEU": "110000",
    "Lyceum": "217500",
    "Mapua": "140000",
    "Miriam": "115000",
    "Saint Louis University": "115000",
    "San Beda": "140000",
    "Silliman University": "140000",
    "St Paul": "120000",
    "St Scholastica": "110000",
    "UA&P": "190000",
    "UE": "81500",
    "Univ. of Pangasinan": "81500",
    "Univ. of San Carlos": "81500",
    "UP Cebu": "81500",
    "UP Diliman": "81500",
    "UP Visayas": "81500",
    "UP Visayas": "81500",
    "UST": "45000",
    "Xavier CDO": "45000"
}